{
  "sections": {
    "main": {
      "type": "main-page",
      "disabled": true,
      "settings": {
        "padding_top": 28,
        "padding_bottom": 28
      }
    },
    "e6ff2520-8950-43ef-b270-700de21448fe": {
      "type": "image-with-text",
      "blocks": {
        "template--16410224328866__e6ff2520-8950-43ef-b270-700de21448fe-heading-1": {
          "type": "heading",
          "settings": {
            "heading": "Urologists and Healthcare Providers — Partner Information",
            "heading_size": "h1",
            "force_h1": true
          }
        },
        "template--16410224328866__e6ff2520-8950-43ef-b270-700de21448fe-text-1": {
          "type": "text",
          "settings": {
            "text": "<p>Information for urologists and healthcare providers starting or engaged in a partnership with Xialla<\/p>",
            "text_style": "body"
          }
        },
        "template--16410224328866__e6ff2520-8950-43ef-b270-700de21448fe-button-1": {
          "type": "button",
          "disabled": true,
          "settings": {
            "button_label": "Button label",
            "button_link": ""
          }
        }
      },
      "block_order": [
        "template--16410224328866__e6ff2520-8950-43ef-b270-700de21448fe-heading-1",
        "template--16410224328866__e6ff2520-8950-43ef-b270-700de21448fe-text-1",
        "template--16410224328866__e6ff2520-8950-43ef-b270-700de21448fe-button-1"
      ],
      "settings": {
        "image": "shopify:\/\/shop_images\/Faysal_Team_Pic.jpg",
        "height": "adapt",
        "desktop_image_width": "medium",
        "layout": "text_first",
        "desktop_content_position": "top",
        "desktop_content_alignment": "left",
        "content_layout": "no-overlap",
        "color_scheme": "background-1",
        "mobile_content_alignment": "left",
        "padding_top": 36,
        "padding_bottom": 36
      }
    },
    "d4cd82c8-186e-43b0-8ac7-4dcbab37f642": {
      "type": "collapsible-content",
      "blocks": {
        "8b77b1ff-909c-4deb-84c8-30da6407dc1d": {
          "type": "collapsible_row",
          "settings": {
            "heading": "About the partnership",
            "icon": "none",
            "row_content": "<p>A partnership with Xialla lets you refer patients to buy Xialla from us directly on our e-commerce website. Your patient benefits from the best venous leak treatment. You benefit from a hassle-free partnership. We benefit from your referrals. <\/p>",
            "page": ""
          }
        },
        "48ab6f8d-23bb-4e76-a592-f528cdc3c948": {
          "type": "collapsible_row",
          "settings": {
            "heading": "Starting a partnership",
            "icon": "none",
            "row_content": "<p>To start a partnership with us, just complete the very short form <a href=\"\/pages\/medical\" title=\"Medical\">here<\/a>.<\/p>",
            "page": ""
          }
        },
        "template--16410224328866__d4cd82c8-186e-43b0-8ac7-4dcbab37f642-collapsible_row-1": {
          "type": "collapsible_row",
          "settings": {
            "heading": "How the partnership works",
            "icon": "none",
            "row_content": "<ol><li>We will send you free Xialla samples. Try a couple on patients and keep one or two to demonstrate.<\/li><li>We'll send you Xialla referral cards.<\/li><li>You hand a referral card to a patient.<\/li><li>The patient buys Xialla on our website. <\/li><\/ol>",
            "page": ""
          }
        },
        "template--16410224328866__d4cd82c8-186e-43b0-8ac7-4dcbab37f642-collapsible_row-2": {
          "type": "collapsible_row",
          "settings": {
            "heading": "Prescribing Xialla",
            "icon": "none",
            "row_content": "<ol><li>Xialla is effective for venous leak-related ED.<\/li><li>For more severe cases, Xialla works well with pumps, injections and oral medication.<\/li><li>Inject before putting on Xialla so the Xialla doesn't interfere with the injection procedure.<\/li><li>Xialla is safer and more comfortable than other rings as it doesn't need to be as tight to be effective.<\/li><li>Xialla can be put on flaccid or erect.<\/li><\/ol><p><\/p>",
            "page": ""
          }
        },
        "140e6914-d51d-41f6-ad0f-b189c18a33e6": {
          "type": "collapsible_row",
          "settings": {
            "heading": "Insurance",
            "icon": "none",
            "row_content": "<p>Xialla is not currently covered by insurance.<\/p>",
            "page": ""
          }
        },
        "0aacb3dd-d8ba-41f8-9f69-6b19a01e952c": {
          "type": "collapsible_row",
          "settings": {
            "heading": "Benefits of Xialla",
            "icon": "none",
            "row_content": "<ul><li>The primary benefit of Xialla is effective treatment of VOD.  <\/li><li>Xialla has <a href=\"\/blogs\/knowledge-center\/the-unique-benefits-of-xialla\" title=\"The unique benefits of Xialla\">several other unique benefits<\/a> as a result of the retraction of the ring toward the base of the penis.<\/li><li>We find customers love hearing about the many benefits and it encourages better effort to achieve success.<\/li><\/ul>",
            "page": ""
          }
        },
        "8dbec830-ab29-42ef-9698-c6b6420d9891": {
          "type": "collapsible_row",
          "settings": {
            "heading": "Overcoming objections",
            "icon": "none",
            "row_content": "<p>Xialla is different. Some men may find it weird. We try to let men know what a remarkable device it really is, so they won't miss an opportunity to possibly fix their problem, and more. <\/p><p>We let men know that Xialla;<\/p><ol><li>is <a href=\"\/pages\/clinical-trials\" title=\"Clinical Trials\">effective<\/a><\/li><li>is <a href=\"https:\/\/www.trustpilot.com\/review\/xialla.com\" title=\"https:\/\/www.trustpilot.com\/review\/xialla.com\">loved<\/a> by many men<\/li><li> is <a href=\"https:\/\/www.trustpilot.com\/review\/xialla.com\" title=\"https:\/\/www.trustpilot.com\/review\/xialla.com\">loved<\/a> by many women<\/li><li>has many <a href=\"\/blogs\/knowledge-center\/the-unique-benefits-of-xialla\" title=\"The unique benefits of Xialla\">benefits<\/a> that no other ring or medication has<\/li><li>is fully <a href=\"\/pages\/customer-support\" title=\"Customer Support\">money-back<\/a> guaranteed<\/li><li>has five star <a href=\"\/pages\/customer-support\" title=\"Customer Support\">customer support<\/a><\/li><\/ol>",
            "page": ""
          }
        },
        "2d7c8514-4ab6-4479-bfcf-e59cd04e9ba3": {
          "type": "collapsible_row",
          "settings": {
            "heading": "Sizing",
            "icon": "none",
            "row_content": "<ul><li>Xialla comes in 3 sizes: Regular, Slender, Thicker.<\/li><li>Sizing is by girth only, not length.<\/li><li>The patient will choose the size from our website at the time of purchase. <\/li><li>We have a sizing chart <a href=\"https:\/\/xialla.com\/blogs\/help\/what-size-should-i-order\" title=\"https:\/\/xialla.com\/blogs\/help\/what-size-should-i-order\">here<\/a> as well as on the product order page<\/li><li>We advise the patient to choose Regular size if unsure. <\/li><li>10% of users change size to Thicker and 10% to Slender.<\/li><\/ul>",
            "page": ""
          }
        },
        "template--16410224328866__d4cd82c8-186e-43b0-8ac7-4dcbab37f642-collapsible_row-3": {
          "type": "collapsible_row",
          "settings": {
            "heading": "Size changes, warranty, money-back guarantee",
            "icon": "none",
            "row_content": "<ul><li>We will exchange the size for a different size for at no charge.<\/li><li>We will replace any broken or defective Xialla at no charge within one year.<\/li><li>We will issue a full refund if Xialla is not effective for the patient, or if the patient is dissatisfied for any reason.<\/li><\/ul>",
            "page": ""
          }
        },
        "205748fc-717b-4eca-a00d-f6e980b06dec": {
          "type": "collapsible_row",
          "settings": {
            "heading": "Patient support",
            "icon": "none",
            "row_content": "<p>We will fully support your patient with five star customer service. <\/p><p>The patient will easily find the support link at the top of the website and on the referral card.<\/p><p>We fully respect the physician\/patient relationship and will refer the patient back to you for medical questions. <\/p>",
            "page": ""
          }
        },
        "98f02a02-2187-4008-a701-d428b10b7de6": {
          "type": "collapsible_row",
          "settings": {
            "heading": "Urologist and healthcare provider support",
            "icon": "none",
            "row_content": "<p>Contact Nigel Shaw at <a href=\"mailto:nshaw@xialla.com\" title=\"mailto:nshaw@xialla.com\">nshaw@xialla.com<\/a>.<\/p>",
            "page": ""
          }
        },
        "template--16410224328866__d4cd82c8-186e-43b0-8ac7-4dcbab37f642-collapsible_row-4": {
          "type": "collapsible_row",
          "settings": {
            "heading": "Samples",
            "icon": "none",
            "row_content": "<p>We will send you a sample pack of Xiallas.<\/p>",
            "page": ""
          }
        },
        "5c791fb4-66a0-4cab-8cca-9396bdf714ad": {
          "type": "collapsible_row",
          "settings": {
            "heading": "Referral cards",
            "icon": "none",
            "row_content": "<ul><li>We will send you referral cards customized with your unique discount code, QR code name and office phone number. <\/li><li>The discount gives the patient 20% off for life.<\/li><li>The card is like a credit card, easy to keep handy and use for repeat purchases of adhesive pads.<\/li><\/ul>",
            "page": ""
          }
        },
        "4d4035f0-369a-44b6-b321-e592f09e5092": {
          "type": "collapsible_row",
          "settings": {
            "heading": "Request additional samples or referral cards",
            "icon": "none",
            "row_content": "<p>We're glad to send you additional samples or referral cards at no charge. <\/p><p><a href=\"mailto:nshaw@xialla.com\" title=\"mailto:nshaw@xialla.com\">Click here to request additional samples or referral cards<\/a>. <\/p><p><em>(First time requesting samples? Click <\/em><a href=\"\/pages\/medical\" title=\"Medical\"><em>here<\/em><\/a><em>.)<\/em><\/p>",
            "page": ""
          }
        }
      },
      "block_order": [
        "8b77b1ff-909c-4deb-84c8-30da6407dc1d",
        "48ab6f8d-23bb-4e76-a592-f528cdc3c948",
        "template--16410224328866__d4cd82c8-186e-43b0-8ac7-4dcbab37f642-collapsible_row-1",
        "template--16410224328866__d4cd82c8-186e-43b0-8ac7-4dcbab37f642-collapsible_row-2",
        "140e6914-d51d-41f6-ad0f-b189c18a33e6",
        "0aacb3dd-d8ba-41f8-9f69-6b19a01e952c",
        "8dbec830-ab29-42ef-9698-c6b6420d9891",
        "2d7c8514-4ab6-4479-bfcf-e59cd04e9ba3",
        "template--16410224328866__d4cd82c8-186e-43b0-8ac7-4dcbab37f642-collapsible_row-3",
        "205748fc-717b-4eca-a00d-f6e980b06dec",
        "98f02a02-2187-4008-a701-d428b10b7de6",
        "template--16410224328866__d4cd82c8-186e-43b0-8ac7-4dcbab37f642-collapsible_row-4",
        "5c791fb4-66a0-4cab-8cca-9396bdf714ad",
        "4d4035f0-369a-44b6-b321-e592f09e5092"
      ],
      "settings": {
        "caption": "",
        "heading": "",
        "heading_size": "h1",
        "heading_alignment": "center",
        "layout": "none",
        "color_scheme": "background-1",
        "container_color_scheme": "background-2",
        "open_first_collapsible_row": false,
        "image_ratio": "adapt",
        "desktop_layout": "image_second",
        "padding_top": 36,
        "padding_bottom": 36
      }
    }
  },
  "order": [
    "main",
    "e6ff2520-8950-43ef-b270-700de21448fe",
    "d4cd82c8-186e-43b0-8ac7-4dcbab37f642"
  ]
}
